README.md
setup.cfg
setup.py
promalyze/__init__.py
promalyze/client.py
promalyze/prometheus_data.py
promalyze/timeseries.py
promalyze/utils.py
promalyze/vector.py
promalyze.egg-info/PKG-INFO
promalyze.egg-info/SOURCES.txt
promalyze.egg-info/dependency_links.txt
promalyze.egg-info/requires.txt
promalyze.egg-info/top_level.txt