Metadata-Version: 1.1
Name: promalyze
Version: 0.0.1
Summary: A a library for querying prometheus and working with the data
Home-page: https://github.com/parabuzzle/promalyze
Author: Michael Heijmans
Author-email: parabuzzle@gmail.com
License: MIT
Keywords: prometheus metrics data timeseries data science
Platform: UNKNOWN
Classifier: Development Status :: 3 - Alpha
Classifier: Intended Audience :: Developers
Classifier: License :: OSI Approved :: MIT License
Classifier: Programming Language :: Python :: 2
Classifier: Programming Language :: Python :: 2.7
Classifier: Programming Language :: Python :: 3
Classifier: Programming Language :: Python :: 3.3
Classifier: Programming Language :: Python :: 3.4
Classifier: Programming Language :: Python :: 3.5
Classifier: Programming Language :: Python :: 3.6
